Workbook

Sheet Инструкция
A1: ЖУРНАЛ УЧЁТА ОЦЕНОК — модуль «Применение ИКТ и цифровых технологий»
A2: Специальность: Техник информационных систем (4S06130105). 96 ч, 39 занятий, форма контроля — дифференцированный зачёт.
A5: НОРМАТИВНАЯ ОСНОВА:
A6: • Приказ МОН РК № 125 (рег. 5191, ред. № 98 от 30.04.2025) — Типовые правила текущего контроля/аттестации ТиПО.
A7: • Приказ МП РК № 263 (рег. 33330) — формы строгой отчётности, Приложение 14 «Журнал учёта теоретического обучения».
A8: • Система оценки: 100-балльная буквенная (A–F), п.3; зачёт — на основе текущего контроля, п.8.
A10: МОДЕЛЬ ОЦЕНИВАНИЯ (веса):
A11: • Практика (zadanie + устная защита) — 40 %
A12: • Тесты (test.gift) — 20 %
A13: • СРС (upr) — 15 %
A14: • Итоговый проект (занятие 38) + защита (занятие 39) — 25 %
A15: ИТОГ % = 0,20·Тесты + 0,40·Практика + 0,15·СРС + 0,25·Проект. Порог зачёта — 50 %.
... A24: AI-устойчивость: практические задания и проект засчитываются только с устной защитой/демонстрацией.

Sheet Занятия
A1: № | B1: Часы | C1: Тема занятия
A2: 1 | B2: 2 | C2: Изучить роль ИКТ и цифровых технологий в разработке и сопровождении информационных систем
A3: 2 | B3: 2 | C3: Изучить устройство ПК, ОС (Windows/Linux) и файловую систему
A4: 3 | B4: 2 | C4: Освоить работу в командной строке/терминале
A5: 4 | B5: 2 | C5: Понять представление и кодирование информации (системы счисления)
A6: 5 | B6: 2 | C6: Оформлять техническую документацию в текстовом редакторе
A7: 6 | B7: 2 | C7: Использовать электронные таблицы для расчётов и данных
A8: 7 | B8: 2 | C8: Создавать презентации для защиты проектов
A9: 8 | B9: 2 | C9: Распознавать сетевые угрозы: фишинг, вирусы, вредоносное ПО
A10: 9 | B10: 2 | C10: Применять основы информационной безопасности и цифровой гигиены
A11: 10 | B11: 2 | C11: Изучить законы РК «Об информатизации» и «О персональных данных»
A12: 11 | B12: 2 | C12: Пользоваться браузерами, поиском и оценкой достоверности информации
A13: 12 | B13: 2 | C13: Работать с облачными сервисами и совместной работой
... A40: 39 | B40: 2 | C40: Защитить итоговый проект и провести рефлексию

Sheet Шкала
A1: Порог % (от) | B1: Буква | C1: GPA | D1: 5-балл | E1: Традиционно | F1: Итог
A2: 0 | B2: F | C2: 0 | D2: 2 | E2: Неудовлетворительно | F2: незачёт
A3: 50 | B3: D | C3: 1 | D3: 3 | E3: Удовлетворительно | F3: зачёт
A4: 55 | B4: D+ | C4: 1.33 | D4: 3 | E4: Удовлетворительно | F4: зачёт
A5: 60 | B5: C- | C5: 1.67 | D5: 3 | E5: Удовлетворительно | F5: зачёт
A6: 65 | B6: C | C6: 2 | D6: 3 | E6: Удовлетворительно | F6: зачёт
A7: 70 | B7: C+ | C7: 2.33 | D7: 3 | E7: Удовлетворительно | F7: зачёт
A8: 75 | B8: B- | C8: 2.67 | D8: 4 | E8: Хорошо | F8: зачёт
A9: 80 | B9: B | C9: 3 | D9: 4 | E9: Хорошо | F9: зачёт
A10: 85 | B10: B+ | C10: 3.33 | D10: 4 | E10: Хорошо | F10: зачёт
A11: 90 | B11: A- | C11: 3.67 | D11: 5 | E11: Отлично | F11: зачёт
A12: 95 | B12: A | C12: 4 | D12: 5 | E12: Отлично | F12: зачёт

Sheet Список
A1: № | B1: ФИО студента
A2: 1
A3: 2
A4: 3
A5: 4
A6: 5
A7: 6
A8: 7
A9: 8
A10: 9
A11: 10
A12: 11
A13: 12
... A26: 25

Sheet Тесты
A1: № | B1: ФИО студента | C1: З01 | D1: З02 | E1: З03 | F1: З04 | G1: З05 | H1: З06 | I1: З07 | J1: З08 | K1: З09 | L1: З10 | M1: З11 | N1: З12 | O1: З13 | P1: З14 | Q1: З15 | R1: З16 | S1: З17 | T1: З18 | U1: З19 | V1: З20 | W1: З21 | X1: З22 | Y1: З23 | Z1: З24 | AA1: З25 | AB1: З26 | AC1: З27 | AD1: З28 | AE1: З29 | AF1: З30 | AG1: З31 | AH1: З32 | AI1: З33 | AJ1: З34 | AK1: З35 | AL1: З36 | AM1: З37 | AN1: З38 | AO1: З39 | AP1: Средний %
A2: =Список!A2 -> 1 | B2: =Список!B2 -> 0 | AP2: =IFERROR(AVERAGE(C2:AO2),"")
A3: =Список!A3 -> 2 | B3: =Список!B3 -> 0 | AP3: =IFERROR(AVERAGE(C3:AO3),"")
A4: =Список!A4 -> 3 | B4: =Список!B4 -> 0 | AP4: =IFERROR(AVERAGE(C4:AO4),"")
A5: =Список!A5 -> 4 | B5: =Список!B5 -> 0 | AP5: =IFERROR(AVERAGE(C5:AO5),"")
A6: =Список!A6 -> 5 | B6: =Список!B6 -> 0 | AP6: =IFERROR(AVERAGE(C6:AO6),"")
A7: =Список!A7 -> 6 | B7: =Список!B7 -> 0 | AP7: =IFERROR(AVERAGE(C7:AO7),"")
A8: =Список!A8 -> 7 | B8: =Список!B8 -> 0 | AP8: =IFERROR(AVERAGE(C8:AO8),"")
A9: =Список!A9 -> 8 | B9: =Список!B9 -> 0 | AP9: =IFERROR(AVERAGE(C9:AO9),"")
A10: =Список!A10 -> 9 | B10: =Список!B10 -> 0 | AP10: =IFERROR(AVERAGE(C10:AO10),"")
A11: =Список!A11 -> 10 | B11: =Список!B11 -> 0 | AP11: =IFERROR(AVERAGE(C11:AO11),"")
A12: =Список!A12 -> 11 | B12: =Список!B12 -> 0 | AP12: =IFERROR(AVERAGE(C12:AO12),"")
A13: =Список!A13 -> 12 | B13: =Список!B13 -> 0 | AP13: =IFERROR(AVERAGE(C13:AO13),"")
... A26: =Список!A26 -> 25 | B26: =Список!B26 -> 0 | AP26: =IFERROR(AVERAGE(C26:AO26),"")

Sheet Практика
A1: № | B1: ФИО студента | C1: З01 | D1: З02 | E1: З03 | F1: З04 | G1: З05 | H1: З06 | I1: З07 | J1: З08 | K1: З09 | L1: З10 | M1: З11 | N1: З12 | O1: З13 | P1: З14 | Q1: З15 | R1: З16 | S1: З17 | T1: З18 | U1: З19 | V1: З20 | W1: З21 | X1: З22 | Y1: З23 | Z1: З24 | AA1: З25 | AB1: З26 | AC1: З27 | AD1: З28 | AE1: З29 | AF1: З30 | AG1: З31 | AH1: З32 | AI1: З33 | AJ1: З34 | AK1: З35 | AL1: З36 | AM1: З37 | AN1: З38 | AO1: З39 | AP1: Средний %
A2: =Список!A2 -> 1 | B2: =Список!B2 -> 0 | AP2: =IFERROR(AVERAGE(C2:AO2),"")
A3: =Список!A3 -> 2 | B3: =Список!B3 -> 0 | AP3: =IFERROR(AVERAGE(C3:AO3),"")
A4: =Список!A4 -> 3 | B4: =Список!B4 -> 0 | AP4: =IFERROR(AVERAGE(C4:AO4),"")
A5: =Список!A5 -> 4 | B5: =Список!B5 -> 0 | AP5: =IFERROR(AVERAGE(C5:AO5),"")
A6: =Список!A6 -> 5 | B6: =Список!B6 -> 0 | AP6: =IFERROR(AVERAGE(C6:AO6),"")
A7: =Список!A7 -> 6 | B7: =Список!B7 -> 0 | AP7: =IFERROR(AVERAGE(C7:AO7),"")
A8: =Список!A8 -> 7 | B8: =Список!B8 -> 0 | AP8: =IFERROR(AVERAGE(C8:AO8),"")
A9: =Список!A9 -> 8 | B9: =Список!B9 -> 0 | AP9: =IFERROR(AVERAGE(C9:AO9),"")
A10: =Список!A10 -> 9 | B10: =Список!B10 -> 0 | AP10: =IFERROR(AVERAGE(C10:AO10),"")
A11: =Список!A11 -> 10 | B11: =Список!B11 -> 0 | AP11: =IFERROR(AVERAGE(C11:AO11),"")
A12: =Список!A12 -> 11 | B12: =Список!B12 -> 0 | AP12: =IFERROR(AVERAGE(C12:AO12),"")
A13: =Список!A13 -> 12 | B13: =Список!B13 -> 0 | AP13: =IFERROR(AVERAGE(C13:AO13),"")
... A26: =Список!A26 -> 25 | B26: =Список!B26 -> 0 | AP26: =IFERROR(AVERAGE(C26:AO26),"")

Sheet СРС
A1: № | B1: ФИО студента | C1: З01 | D1: З02 | E1: З03 | F1: З04 | G1: З05 | H1: З06 | I1: З07 | J1: З08 | K1: З09 | L1: З10 | M1: З11 | N1: З12 | O1: З13 | P1: З14 | Q1: З15 | R1: З16 | S1: З17 | T1: З18 | U1: З19 | V1: З20 | W1: З21 | X1: З22 | Y1: З23 | Z1: З24 | AA1: З25 | AB1: З26 | AC1: З27 | AD1: З28 | AE1: З29 | AF1: З30 | AG1: З31 | AH1: З32 | AI1: З33 | AJ1: З34 | AK1: З35 | AL1: З36 | AM1: З37 | AN1: З38 | AO1: З39 | AP1: Средний %
A2: =Список!A2 -> 1 | B2: =Список!B2 -> 0 | AP2: =IFERROR(AVERAGE(C2:AO2),"")
A3: =Список!A3 -> 2 | B3: =Список!B3 -> 0 | AP3: =IFERROR(AVERAGE(C3:AO3),"")
A4: =Список!A4 -> 3 | B4: =Список!B4 -> 0 | AP4: =IFERROR(AVERAGE(C4:AO4),"")
A5: =Список!A5 -> 4 | B5: =Список!B5 -> 0 | AP5: =IFERROR(AVERAGE(C5:AO5),"")
A6: =Список!A6 -> 5 | B6: =Список!B6 -> 0 | AP6: =IFERROR(AVERAGE(C6:AO6),"")
A7: =Список!A7 -> 6 | B7: =Список!B7 -> 0 | AP7: =IFERROR(AVERAGE(C7:AO7),"")
A8: =Список!A8 -> 7 | B8: =Список!B8 -> 0 | AP8: =IFERROR(AVERAGE(C8:AO8),"")
A9: =Список!A9 -> 8 | B9: =Список!B9 -> 0 | AP9: =IFERROR(AVERAGE(C9:AO9),"")
A10: =Список!A10 -> 9 | B10: =Список!B10 -> 0 | AP10: =IFERROR(AVERAGE(C10:AO10),"")
A11: =Список!A11 -> 10 | B11: =Список!B11 -> 0 | AP11: =IFERROR(AVERAGE(C11:AO11),"")
A12: =Список!A12 -> 11 | B12: =Список!B12 -> 0 | AP12: =IFERROR(AVERAGE(C12:AO12),"")
A13: =Список!A13 -> 12 | B13: =Список!B13 -> 0 | AP13: =IFERROR(AVERAGE(C13:AO13),"")
... A26: =Список!A26 -> 25 | B26: =Список!B26 -> 0 | AP26: =IFERROR(AVERAGE(C26:AO26),"")

Sheet Итоги
A1: № | B1: ФИО студента | C1: Тесты % | D1: Практика % | E1: СРС % | F1: Проект-38 % | G1: Защита-39 % | H1: Проект % | I1: ИТОГ % | J1: Буква | K1: GPA | L1: 5-балл | M1: Зачёт | N1: Рейтинг допуска %
A2: =Список!A2 -> 1 | B2: =Список!B2 -> 0 | C2: =Тесты!AP2 | D2: =Практика!AP2 | E2: =СРС!AP2 | H2: =IFERROR(AVERAGE(F2:G2),"") | I2: =0.2*N(C2)+0.4*N(D2)+0.15*N(E2)+0.25*N(H2) -> 0 | J2: =IFERROR(VLOOKUP(I2,Шкала!$A$2:$F$12,2,TRUE),"") -> F | K2: =IFERROR(VLOOKUP(I2,Шкала!$A$2:$F$12,3,TRUE),"") -> 0 | L2: =IFERROR(VLOOKUP(I2,Шкала!$A$2:$F$12,4,TRUE),"") -> 2 | M2: =IF(I2>=50,"зачёт","незачёт") -> незачёт | N2: =IFERROR((0.2*N(C2)+0.4*N(D2)+0.15*N(E2))/0.75,"") -> 0
A3: =Список!A3 -> 2 | B3: =Список!B3 -> 0 | C3: =Тесты!AP3 | D3: =Практика!AP3 | E3: =СРС!AP3 | H3: =IFERROR(AVERAGE(F3:G3),"") | I3: =0.2*N(C3)+0.4*N(D3)+0.15*N(E3)+0.25*N(H3) -> 0 | J3: =IFERROR(VLOOKUP(I3,Шкала!$A$2:$F$12,2,TRUE),"") -> F | K3: =IFERROR(VLOOKUP(I3,Шкала!$A$2:$F$12,3,TRUE),"") -> 0 | L3: =IFERROR(VLOOKUP(I3,Шкала!$A$2:$F$12,4,TRUE),"") -> 2 | M3: =IF(I3>=50,"зачёт","незачёт") -> незачёт | N3: =IFERROR((0.2*N(C3)+0.4*N(D3)+0.15*N(E3))/0.75,"") -> 0
A4: =Список!A4 -> 3 | B4: =Список!B4 -> 0 | C4: =Тесты!AP4 | D4: =Практика!AP4 | E4: =СРС!AP4 | H4: =IFERROR(AVERAGE(F4:G4),"") | I4: =0.2*N(C4)+0.4*N(D4)+0.15*N(E4)+0.25*N(H4) -> 0 | J4: =IFERROR(VLOOKUP(I4,Шкала!$A$2:$F$12,2,TRUE),"") -> F | K4: =IFERROR(VLOOKUP(I4,Шкала!$A$2:$F$12,3,TRUE),"") -> 0 | L4: =IFERROR(VLOOKUP(I4,Шкала!$A$2:$F$12,4,TRUE),"") -> 2 | M4: =IF(I4>=50,"зачёт","незачёт") -> незачёт | N4: =IFERROR((0.2*N(C4)+0.4*N(D4)+0.15*N(E4))/0.75,"") -> 0
A5: =Список!A5 -> 4 | B5: =Список!B5 -> 0 | C5: =Тесты!AP5 | D5: =Практика!AP5 | E5: =СРС!AP5 | H5: =IFERROR(AVERAGE(F5:G5),"") | I5: =0.2*N(C5)+0.4*N(D5)+0.15*N(E5)+0.25*N(H5) -> 0 | J5: =IFERROR(VLOOKUP(I5,Шкала!$A$2:$F$12,2,TRUE),"") -> F | K5: =IFERROR(VLOOKUP(I5,Шкала!$A$2:$F$12,3,TRUE),"") -> 0 | L5: =IFERROR(VLOOKUP(I5,Шкала!$A$2:$F$12,4,TRUE),"") -> 2 | M5: =IF(I5>=50,"зачёт","незачёт") -> незачёт | N5: =IFERROR((0.2*N(C5)+0.4*N(D5)+0.15*N(E5))/0.75,"") -> 0
A6: =Список!A6 -> 5 | B6: =Список!B6 -> 0 | C6: =Тесты!AP6 | D6: =Практика!AP6 | E6: =СРС!AP6 | H6: =IFERROR(AVERAGE(F6:G6),"") | I6: =0.2*N(C6)+0.4*N(D6)+0.15*N(E6)+0.25*N(H6) -> 0 | J6: =IFERROR(VLOOKUP(I6,Шкала!$A$2:$F$12,2,TRUE),"") -> F | K6: =IFERROR(VLOOKUP(I6,Шкала!$A$2:$F$12,3,TRUE),"") -> 0 | L6: =IFERROR(VLOOKUP(I6,Шкала!$A$2:$F$12,4,TRUE),"") -> 2 | M6: =IF(I6>=50,"зачёт","незачёт") -> незачёт | N6: =IFERROR((0.2*N(C6)+0.4*N(D6)+0.15*N(E6))/0.75,"") -> 0
A7: =Список!A7 -> 6 | B7: =Список!B7 -> 0 | C7: =Тесты!AP7 | D7: =Практика!AP7 | E7: =СРС!AP7 | H7: =IFERROR(AVERAGE(F7:G7),"") | I7: =0.2*N(C7)+0.4*N(D7)+0.15*N(E7)+0.25*N(H7) -> 0 | J7: =IFERROR(VLOOKUP(I7,Шкала!$A$2:$F$12,2,TRUE),"") -> F | K7: =IFERROR(VLOOKUP(I7,Шкала!$A$2:$F$12,3,TRUE),"") -> 0 | L7: =IFERROR(VLOOKUP(I7,Шкала!$A$2:$F$12,4,TRUE),"") -> 2 | M7: =IF(I7>=50,"зачёт","незачёт") -> незачёт | N7: =IFERROR((0.2*N(C7)+0.4*N(D7)+0.15*N(E7))/0.75,"") -> 0
A8: =Список!A8 -> 7 | B8: =Список!B8 -> 0 | C8: =Тесты!AP8 | D8: =Практика!AP8 | E8: =СРС!AP8 | H8: =IFERROR(AVERAGE(F8:G8),"") | I8: =0.2*N(C8)+0.4*N(D8)+0.15*N(E8)+0.25*N(H8) -> 0 | J8: =IFERROR(VLOOKUP(I8,Шкала!$A$2:$F$12,2,TRUE),"") -> F | K8: =IFERROR(VLOOKUP(I8,Шкала!$A$2:$F$12,3,TRUE),"") -> 0 | L8: =IFERROR(VLOOKUP(I8,Шкала!$A$2:$F$12,4,TRUE),"") -> 2 | M8: =IF(I8>=50,"зачёт","незачёт") -> незачёт | N8: =IFERROR((0.2*N(C8)+0.4*N(D8)+0.15*N(E8))/0.75,"") -> 0
A9: =Список!A9 -> 8 | B9: =Список!B9 -> 0 | C9: =Тесты!AP9 | D9: =Практика!AP9 | E9: =СРС!AP9 | H9: =IFERROR(AVERAGE(F9:G9),"") | I9: =0.2*N(C9)+0.4*N(D9)+0.15*N(E9)+0.25*N(H9) -> 0 | J9: =IFERROR(VLOOKUP(I9,Шкала!$A$2:$F$12,2,TRUE),"") -> F | K9: =IFERROR(VLOOKUP(I9,Шкала!$A$2:$F$12,3,TRUE),"") -> 0 | L9: =IFERROR(VLOOKUP(I9,Шкала!$A$2:$F$12,4,TRUE),"") -> 2 | M9: =IF(I9>=50,"зачёт","незачёт") -> незачёт | N9: =IFERROR((0.2*N(C9)+0.4*N(D9)+0.15*N(E9))/0.75,"") -> 0
A10: =Список!A10 -> 9 | B10: =Список!B10 -> 0 | C10: =Тесты!AP10 | D10: =Практика!AP10 | E10: =СРС!AP10 | H10: =IFERROR(AVERAGE(F10:G10),"") | I10: =0.2*N(C10)+0.4*N(D10)+0.15*N(E10)+0.25*N(H10) -> 0 | J10: =IFERROR(VLOOKUP(I10,Шкала!$A$2:$F$12,2,TRUE),"") -> F | K10: =IFERROR(VLOOKUP(I10,Шкала!$A$2:$F$12,3,TRUE),"") -> 0 | L10: =IFERROR(VLOOKUP(I10,Шкала!$A$2:$F$12,4,TRUE),"") -> 2 | M10: =IF(I10>=50,"зачёт","незачёт") -> незачёт | N10: =IFERROR((0.2*N(C10)+0.4*N(D10)+0.15*N(E10))/0.75,"") -> 0
A11: =Список!A11 -> 10 | B11: =Список!B11 -> 0 | C11: =Тесты!AP11 | D11: =Практика!AP11 | E11: =СРС!AP11 | H11: =IFERROR(AVERAGE(F11:G11),"") | I11: =0.2*N(C11)+0.4*N(D11)+0.15*N(E11)+0.25*N(H11) -> 0 | J11: =IFERROR(VLOOKUP(I11,Шкала!$A$2:$F$12,2,TRUE),"") -> F | K11: =IFERROR(VLOOKUP(I11,Шкала!$A$2:$F$12,3,TRUE),"") -> 0 | L11: =IFERROR(VLOOKUP(I11,Шкала!$A$2:$F$12,4,TRUE),"") -> 2 | M11: =IF(I11>=50,"зачёт","незачёт") -> незачёт | N11: =IFERROR((0.2*N(C11)+0.4*N(D11)+0.15*N(E11))/0.75,"") -> 0
A12: =Список!A12 -> 11 | B12: =Список!B12 -> 0 | C12: =Тесты!AP12 | D12: =Практика!AP12 | E12: =СРС!AP12 | H12: =IFERROR(AVERAGE(F12:G12),"") | I12: =0.2*N(C12)+0.4*N(D12)+0.15*N(E12)+0.25*N(H12) -> 0 | J12: =IFERROR(VLOOKUP(I12,Шкала!$A$2:$F$12,2,TRUE),"") -> F | K12: =IFERROR(VLOOKUP(I12,Шкала!$A$2:$F$12,3,TRUE),"") -> 0 | L12: =IFERROR(VLOOKUP(I12,Шкала!$A$2:$F$12,4,TRUE),"") -> 2 | M12: =IF(I12>=50,"зачёт","незачёт") -> незачёт | N12: =IFERROR((0.2*N(C12)+0.4*N(D12)+0.15*N(E12))/0.75,"") -> 0
A13: =Список!A13 -> 12 | B13: =Список!B13 -> 0 | C13: =Тесты!AP13 | D13: =Практика!AP13 | E13: =СРС!AP13 | H13: =IFERROR(AVERAGE(F13:G13),"") | I13: =0.2*N(C13)+0.4*N(D13)+0.15*N(E13)+0.25*N(H13) -> 0 | J13: =IFERROR(VLOOKUP(I13,Шкала!$A$2:$F$12,2,TRUE),"") -> F | K13: =IFERROR(VLOOKUP(I13,Шкала!$A$2:$F$12,3,TRUE),"") -> 0 | L13: =IFERROR(VLOOKUP(I13,Шкала!$A$2:$F$12,4,TRUE),"") -> 2 | M13: =IF(I13>=50,"зачёт","незачёт") -> незачёт | N13: =IFERROR((0.2*N(C13)+0.4*N(D13)+0.15*N(E13))/0.75,"") -> 0
... A26: =Список!A26 -> 25 | B26: =Список!B26 -> 0 | C26: =Тесты!AP26 | D26: =Практика!AP26 | E26: =СРС!AP26 | H26: =IFERROR(AVERAGE(F26:G26),"") | I26: =0.2*N(C26)+0.4*N(D26)+0.15*N(E26)+0.25*N(H26) -> 0 | J26: =IFERROR(VLOOKUP(I26,Шкала!$A$2:$F$12,2,TRUE),"") -> F | K26: =IFERROR(VLOOKUP(I26,Шкала!$A$2:$F$12,3,TRUE),"") -> 0 | L26: =IFERROR(VLOOKUP(I26,Шкала!$A$2:$F$12,4,TRUE),"") -> 2 | M26: =IF(I26>=50,"зачёт","незачёт") -> незачёт | N26: =IFERROR((0.2*N(C26)+0.4*N(D26)+0.15*N(E26))/0.75,"") -> 0
